MANIFEST.in
README.rst
setup.py
django_shared.egg-info/PKG-INFO
django_shared.egg-info/SOURCES.txt
django_shared.egg-info/dependency_links.txt
django_shared.egg-info/requires.txt
django_shared.egg-info/top_level.txt
shared/__init__.py
shared/app_settings.py
shared/configurations.py
shared/models.py
shared/utils.py
shared/management/commands/__init__.py
shared/management/commands/settings.py
shared/templatetags/__init__.py
shared/templatetags/copyrights.py