Metadata-Version: 1.1
Name: django-shared
Version: 0.0.1
Summary: Additional Django functionality
Home-page: https://github.com/dArignac/shared
Author: Alexander Herrmann
Author-email: darignac@gmail.com
License: MIT
Platform: UNKNOWN
Classifier: Development Status :: 4 - Beta
Classifier: Intended Audience :: Developers
Classifier: License :: OSI Approved :: MIT License
Classifier: Natural Language :: English
Classifier: Operating System :: POSIX :: Linux
Classifier: Programming Language :: Python :: 3.4
Classifier: Topic :: Utilities
